LICENSE
README.md
setup.py
pyserve/__init__.py
pyserve/abc.py
pyserve/threading.py
pyserve/transport.py
pyserve3.egg-info/PKG-INFO
pyserve3.egg-info/SOURCES.txt
pyserve3.egg-info/dependency_links.txt
pyserve3.egg-info/requires.txt
pyserve3.egg-info/top_level.txt