Metadata-Version: 2.1
Name: pyserve3
Version: 0.0.7
Summary: Unify SocketServer Implementations based on a Session Model
Home-page: https://github.com/imgurbot12/pyserve
Author: Andrew Scott
Author-email: imgurbot12@gmail.com
License: MIT
Platform: UNKNOWN
Classifier: Programming Language :: Python :: 3
Classifier: License :: OSI Approved :: MIT License
Classifier: Operating System :: OS Independent
Requires-Python: >=3.8
